nifty/__init__.py
nifty/config.py
nifty/cl/__init__.py
nifty/cl/any_array.py
nifty/cl/domain_tuple.py
nifty/cl/ducc_dispatch.py
nifty/cl/evidence_lower_bound.py
nifty/cl/extra.py
nifty/cl/field.py
nifty/cl/linearization.py
nifty/cl/logger.py
nifty/cl/multi_domain.py
nifty/cl/multi_field.py
nifty/cl/operator_spectrum.py
nifty/cl/operator_tree_optimiser.py
nifty/cl/plot.py
nifty/cl/pointwise.py
nifty/cl/probing.py
nifty/cl/random.py
nifty/cl/sugar.py
nifty/cl/utilities.py
nifty/cl/domains/__init__.py
nifty/cl/domains/dof_space.py
nifty/cl/domains/domain.py
nifty/cl/domains/gl_space.py
nifty/cl/domains/hp_space.py
nifty/cl/domains/lm_space.py
nifty/cl/domains/power_space.py
nifty/cl/domains/rg_space.py
nifty/cl/domains/structured_domain.py
nifty/cl/domains/unstructured_domain.py
nifty/cl/library/__init__.py
nifty/cl/library/adjust_variances.py
nifty/cl/library/correlated_fields.py
nifty/cl/library/correlated_fields_simple.py
nifty/cl/library/dynamic_operator.py
nifty/cl/library/light_cone_operator.py
nifty/cl/library/los_response.py
nifty/cl/library/nft.py
nifty/cl/library/special_distributions.py
nifty/cl/library/variational_models.py
nifty/cl/library/wiener_filter_curvature.py
nifty/cl/minimization/__init__.py
nifty/cl/minimization/conjugate_gradient.py
nifty/cl/minimization/descent_minimizers.py
nifty/cl/minimization/energy.py
nifty/cl/minimization/energy_adapter.py
nifty/cl/minimization/iteration_controllers.py
nifty/cl/minimization/kl_energies.py
nifty/cl/minimization/line_search.py
nifty/cl/minimization/minimizer.py
nifty/cl/minimization/nonlinear_cg.py
nifty/cl/minimization/optimize_kl.py
nifty/cl/minimization/quadratic_energy.py
nifty/cl/minimization/sample_list.py
nifty/cl/minimization/scipy_minimizer.py
nifty/cl/minimization/stochastic_minimizer.py
nifty/cl/minimization/config/__init__.py
nifty/cl/minimization/config/optimize_kl_config.py
nifty/cl/operators/__init__.py
nifty/cl/operators/adder.py
nifty/cl/operators/block_diagonal_operator.py
nifty-9.1.0.dist-info/licenses/COPYING
nifty-9.1.0.dist-info/METADATA
nifty-9.1.0.dist-info/WHEEL
nifty-9.1.0.dist-info/top_level.txt
nifty-9.1.0.dist-info/RECORD
