Metadata-Version: 2.4
Name: nifty
Version: 9.1.0
Summary: Probabilistic programming framework for signal inference algorithms that operate regardless of the underlying grids and their resolutions
Author-email: Martin Reinecke <martin@mpa-garching.mpg.de>
License: GPL-3.0-or-later
Project-URL: Homepage, https://github.com/nifty-ppl/nifty
Project-URL: Source Code, https://github.com/nifty-ppl/nifty
Project-URL: Bug Tracker, https://github.com/nifty-ppl/nifty/issues
Project-URL: Documentation, https://ift.pages.mpcdf.de/nifty/
Project-URL: Changelog, https://github.com/NIFTy-PPL/NIFTy/blob/NIFTy_8/ChangeLog.md
Classifier: Development Status :: 5 - Production/Stable
Classifier: Intended Audience :: Science/Research
Classifier: Topic :: Scientific/Engineering :: Mathematics
Classifier: Topic :: Scientific/Engineering :: Physics
Classifier: Operating System :: OS Independent
Classifier: Programming Language :: Python
Requires-Python: >=3.10
License-File: COPYING
Requires-Dist: numpy>=1.17.0
Requires-Dist: scipy>=1.9.0
Provides-Extra: re
Requires-Dist: jax!=0.4.31,!=0.4.32,!=0.4.33,!=0.4.34,!=0.4.35,!=0.4.36,!=0.4.37,!=0.4.38,!=0.6.0,<0.6.0,>=0.4.20; extra == "re"
Requires-Dist: jaxlib!=0.4.31,!=0.4.32,!=0.4.33,!=0.4.34,!=0.4.35,!=0.4.36,!=0.4.37,!=0.4.38,!=0.6.0,<0.6.0,>=0.4.20; extra == "re"
Requires-Dist: jaxbind; extra == "re"
Requires-Dist: ducc0>=0.27.0; extra == "re"
Requires-Dist: healpy; extra == "re"
Provides-Extra: cl-native
Requires-Dist: ducc0>=0.27.0; extra == "cl-native"
Provides-Extra: cl-gpu
Requires-Dist: cupy; extra == "cl-gpu"
Requires-Dist: pyvkfft; extra == "cl-gpu"
Provides-Extra: cl-parallel
Requires-Dist: mpi4py; extra == "cl-parallel"
Provides-Extra: cl-util
Requires-Dist: h5py; extra == "cl-util"
Requires-Dist: matplotlib; extra == "cl-util"
Provides-Extra: doc
Requires-Dist: sphinx<8.2; extra == "doc"
Requires-Dist: pydata-sphinx-theme; extra == "doc"
Requires-Dist: sphinxcontrib-bibtex; extra == "doc"
Requires-Dist: myst-parser; extra == "doc"
Requires-Dist: jupyter; extra == "doc"
Requires-Dist: nbconvert; extra == "doc"
Requires-Dist: jupytext; extra == "doc"
Provides-Extra: test
Requires-Dist: pytest; extra == "test"
Requires-Dist: pytest-cov; extra == "test"
Requires-Dist: pytest-xdist; extra == "test"
Requires-Dist: ducc0; extra == "test"
Requires-Dist: nifty[re]; extra == "test"
Requires-Dist: nifty[cl_util]; extra == "test"
Provides-Extra: all
Requires-Dist: nifty[cl_native,cl_parallel,cl_util,doc,re,test]; extra == "all"
Dynamic: license-file
